Gmap_data/Google_map.py
Gmap_data/__init__.py
Gmap_export-0.0.1.dist-info/LICENSE.txt
Gmap_export-0.0.1.dist-info/METADATA
Gmap_export-0.0.1.dist-info/WHEEL
Gmap_export-0.0.1.dist-info/top_level.txt
Gmap_export-0.0.1.dist-info/RECORD
