Metadata-Version: 2.1
Name: Gmap_export
Version: 0.0.1
Summary: A package to Export google map data
Author: Developer Ashok puri And Pawan yadav
Author-email: developer1.infinity@gmail.com
Keywords: python,tutorial,Google map,developerpawan
Classifier: Development Status :: 1 - Planning
Classifier: Intended Audience :: Developers
Classifier: Programming Language :: Python :: 3
Classifier: Operating System :: Unix
Classifier: Operating System :: MacOS :: MacOS X
Classifier: Operating System :: Microsoft :: Windows
License-File: LICENSE.txt
